src/main/icons/Icon.ico
src/main/icons/README.md
src/main/icons/base/16.png
src/main/icons/base/24.png
src/main/icons/base/32.png
src/main/icons/base/48.png
src/main/icons/base/64.png
src/main/icons/linux/1024.png
src/main/icons/linux/128.png
src/main/icons/linux/256.png
src/main/icons/linux/512.png
src/main/icons/mac/1024.png
src/main/icons/mac/128.png
src/main/icons/mac/256.png
src/main/icons/mac/512.png
src/main/python/__init__.py
src/main/python/main.py
src/main/resources/base/txt2mobi3/resources/img/default_cover.png
src/main/resources/linux/txt2mobi3/resources/kindlegen/linux/kindlegen
src/main/resources/mac/txt2mobi3/resources/kindlegen/mac/kindlegen
src/main/resources/windows/txt2mobi3/resources/kindlegen/win32/kindlegen.exe
txt2mobi3_app-0.2.1.dist-info/LICENSE
txt2mobi3_app-0.2.1.dist-info/METADATA
txt2mobi3_app-0.2.1.dist-info/WHEEL
txt2mobi3_app-0.2.1.dist-info/entry_points.txt
txt2mobi3_app-0.2.1.dist-info/top_level.txt
txt2mobi3_app-0.2.1.dist-info/RECORD
