Metadata-Version: 2.1
Name: txt2mobi3-app
Version: 0.2.1
Summary: A PyQt5 application for converting Chinese novel txt files into Kindle mobi files.
Home-page: https://github.com/renweizhukov/txt2mobi3_app
Author: Wei Ren
Author-email: renwei2004@gmail.com
License: UNKNOWN
Project-URL: Source, https://github.com/renweizhukov/txt2mobi3_app
Project-URL: Documentation, https://github.com/renweizhukov/txt2mobi3_app
Project-URL: Bug Reports, https://github.com/renweizhukov/txt2mobi3_app/issues
Keywords: txt mobi python3 pyqt5
Platform: UNKNOWN
Classifier: Development Status :: 4 - Beta
Classifier: Intended Audience :: End Users/Desktop
Classifier: Topic :: Text Processing :: General
Classifier: License :: OSI Approved :: GNU General Public License v3 (GPLv3)
Classifier: Programming Language :: Python :: 3
Requires-Python: >=3
Requires-Dist: fbs
Requires-Dist: PyQt5
Requires-Dist: setuptools
Requires-Dist: txt2mobi3
